pytest_tagging/__init__.py
pytest_tagging/choices.py
pytest_tagging/plugin.py
pytest_tagging/selector.py
pytest_tagging/utils.py
pytest_tagging-1.5.3.dist-info/LICENSE
pytest_tagging-1.5.3.dist-info/METADATA
pytest_tagging-1.5.3.dist-info/WHEEL
pytest_tagging-1.5.3.dist-info/entry_points.txt
pytest_tagging-1.5.3.dist-info/RECORD
