Metadata-Version: 2.1
Name: pytest_tagging
Version: 1.5.3
Summary: a pytest plugin to tag tests
Home-page: https://github.com/scastlara/pytest-tagging
License: MIT
Author: Sergio Castillo
Author-email: s.cast.lara@gmail.com
Requires-Python: >=3.8,<4.0
Classifier: License :: OSI Approved :: MIT License
Classifier: Programming Language :: Python :: 3
Classifier: Programming Language :: Python :: 3.8
Classifier: Programming Language :: Python :: 3.9
Classifier: Programming Language :: Python :: 3.10
Classifier: Programming Language :: Python :: 3.11
Classifier: Programming Language :: Python :: 3.12
Requires-Dist: pytest (>=7.1.3,<8.0.0)
Project-URL: Repository, https://github.com/scastlara/pytest-tagging
